pytemscript/__init__.py
pytemscript/microscope.py
pytemscript/clients/__init__.py
pytemscript/clients/base_client.py
pytemscript/clients/com_client.py
pytemscript/clients/socket_client.py
pytemscript/clients/utapi_client.py
pytemscript/modules/__init__.py
pytemscript/modules/acquisition.py
pytemscript/modules/apertures.py
pytemscript/modules/autoloader.py
pytemscript/modules/energyfilter.py
pytemscript/modules/extras.py
pytemscript/modules/gun.py
pytemscript/modules/illumination.py
pytemscript/modules/lowdose.py
pytemscript/modules/optics.py
pytemscript/modules/piezo_stage.py
pytemscript/modules/projection.py
pytemscript/modules/stage.py
pytemscript/modules/stem.py
pytemscript/modules/temperature.py
pytemscript/modules/userbuttons.py
pytemscript/modules/userdoor.py
pytemscript/modules/vacuum.py
pytemscript/plugins/__init__.py
pytemscript/plugins/calgetter.py
pytemscript/plugins/tecnai_ccd.py
pytemscript/server/__init__.py
pytemscript/server/run.py
pytemscript/server/socket_server.py
pytemscript/utils/__init__.py
pytemscript/utils/constants.py
pytemscript/utils/describe_grpc.py
pytemscript/utils/enums.py
pytemscript/utils/misc.py
pytemscript/utils/parse_typelib.py
pytemscript-3.0.dist-info/licenses/LICENSE_BSD
pytemscript-3.0.dist-info/licenses/LICENSE_GPL
tests/__init__.py
tests/test_acquisition.py
tests/test_calgetter.py
tests/test_events.py
tests/test_feg_regs.py
tests/test_microscope.py
tests/test_speed.py
pytemscript-3.0.dist-info/METADATA
pytemscript-3.0.dist-info/WHEEL
pytemscript-3.0.dist-info/entry_points.txt
pytemscript-3.0.dist-info/top_level.txt
pytemscript-3.0.dist-info/RECORD
