Metadata-Version: 2.4
Name: pytemscript
Version: 3.0
Summary: TEM Scripting adapter for FEI/TFS microscopes
Home-page: https://github.com/azazellochg/pytemscript
Author: Tore Niermann, Grigory Sharov
Author-email: tore.niermann@tu-berlin.de, gsharov@mrc-lmb.cam.ac.uk
License: GNU General Public License v3 (GPLv3)
Project-URL: Source, https://github.com/azazellochg/pytemscript
Project-URL: Documentation, https://pytemscript.readthedocs.io/
Keywords: TEM python
Platform: any
Classifier: Development Status :: 4 - Beta
Classifier: Intended Audience :: Science/Research
Classifier: Intended Audience :: Developers
Classifier: Operating System :: OS Independent
Classifier: Programming Language :: Python :: 3.4
Classifier: Programming Language :: Python :: 3.8
Classifier: Programming Language :: Python :: 3.9
Classifier: Programming Language :: Python :: 3.10
Classifier: Programming Language :: Python :: 3.11
Classifier: Programming Language :: Python :: 3.12
Classifier: Topic :: Scientific/Engineering
Classifier: Topic :: Software Development :: Libraries
Classifier: License :: OSI Approved :: GNU General Public License v3 (GPLv3)
Requires-Python: >=3.4
License-File: LICENSE_BSD
License-File: LICENSE_GPL
Requires-Dist: comtypes>=1.2.1
Requires-Dist: mrcfile
Requires-Dist: numpy
Requires-Dist: pillow
Provides-Extra: dev
Requires-Dist: matplotlib; extra == "dev"
Requires-Dist: mypy; extra == "dev"
Provides-Extra: utapi
Requires-Dist: grpcio; extra == "utapi"
Requires-Dist: grpcio-tools; extra == "utapi"
Requires-Dist: protobuf; extra == "utapi"
Dynamic: author
Dynamic: author-email
Dynamic: classifier
Dynamic: description
Dynamic: description-content-type
Dynamic: home-page
Dynamic: keywords
Dynamic: license
Dynamic: license-file
Dynamic: platform
Dynamic: project-url
Dynamic: provides-extra
Dynamic: requires-dist
Dynamic: requires-python
Dynamic: summary
